fhict_cb_01/__init__.py
fhict_cb_01/custom_telemetrix.py
fhict_cb_01-0.2.2.dist-info/LICENSE.txt
fhict_cb_01-0.2.2.dist-info/METADATA
fhict_cb_01-0.2.2.dist-info/WHEEL
fhict_cb_01-0.2.2.dist-info/top_level.txt
fhict_cb_01-0.2.2.dist-info/RECORD
