Metadata-Version: 2.1
Name: fhict-cb-01
Version: 0.2.2
Summary: UNKNOWN
Home-page: https://github.com/adamatei/pypi-package
Author: Mark Beks et al
Author-email: m.beks@fontys.nl
License: Fontys
Keywords: FHICT Python support package
Platform: UNKNOWN
Requires-Python: >=3.7.0
License-File: LICENSE.txt
Requires-Dist: flask-login
Requires-Dist: flask-sqlalchemy
Requires-Dist: flask (>=2.0.2)
Requires-Dist: sqlalchemy
Requires-Dist: telemetrix
